README
setup.py
test/test_prefix_handling.py
test/test_safe_mode.py
test/test_table_error.py
tiddlywebplugins/__init__.py
tiddlywebplugins/wikklytextrender.py
tiddlywebplugins.wikklytextrender.egg-info/PKG-INFO
tiddlywebplugins.wikklytextrender.egg-info/SOURCES.txt
tiddlywebplugins.wikklytextrender.egg-info/dependency_links.txt
tiddlywebplugins.wikklytextrender.egg-info/namespace_packages.txt
tiddlywebplugins.wikklytextrender.egg-info/not-zip-safe
tiddlywebplugins.wikklytextrender.egg-info/requires.txt
tiddlywebplugins.wikklytextrender.egg-info/top_level.txt