Metadata-Version: 1.0
Name: tiddlywebplugins.wikklytextrender
Version: 0.8
Summary: A TiddlyWeb plugin to render TiddlyWiki markup to HTML, server-side.
Home-page: http://pypi.python.org/pypi/tiddlywebplugins.wikklytextrender
Author: Chris Dent
Author-email: cdent@peermore.com
License: UNKNOWN
Platform: Posix; MacOS X; Windows
